agent_manager_sdk/__init__.py
agent_manager_sdk/app.py
agent_manager_sdk/celery_worker.py
agent_manager_sdk/config.py
agent_manager_sdk/migrate.py
agent_manager_sdk/secrets_to_azure.py
agent_manager_sdk/app_extensions/celery.py
agent_manager_sdk/app_extensions/db_ext.py
agent_manager_sdk/app_libs/errors.py
agent_manager_sdk/app_libs/exception.py
agent_manager_sdk/app_libs/external_api.py
agent_manager_sdk/app_libs/helper.py
agent_manager_sdk/app_libs/json_in_md_parser.py
agent_manager_sdk/app_libs/login.py
agent_manager_sdk/app_libs/wraps.py
agent_manager_sdk/celery_tasks/tasks.py
agent_manager_sdk/cli/main.py
agent_manager_sdk/controllers/console/__init__.py
agent_manager_sdk/controllers/console/wraps.py
agent_manager_sdk/controllers/console/app/error.py
agent_manager_sdk/controllers/console/app/search.py
agent_manager_sdk/controllers/console/app/workflow.py
agent_manager_sdk/controllers/console/miniapps/dnd/endpoints.py
agent_manager_sdk/controllers/web/workflow.py
agent_manager_sdk/core/app/app_config/__init__.py
agent_manager_sdk/core/app/app_config/entities.py
agent_manager_sdk/core/app/apps/__init__.py
agent_manager_sdk/core/app/apps/base_app_queue_manager.py
agent_manager_sdk/core/app/entities/__init__.py
agent_manager_sdk/core/app/entities/app_invoke_entities.py
agent_manager_sdk/core/app/entities/queue_app_entities.py
agent_manager_sdk/core/callback_handler/__init__.py
agent_manager_sdk/core/callback_handler/agent_tool_callback_handler.py
agent_manager_sdk/core/callback_handler/workflow_tool_callback_handler.py
agent_manager_sdk/core/entities/__init__.py
agent_manager_sdk/core/entities/agent_entities.py
agent_manager_sdk/core/entities/model_entities.py
agent_manager_sdk/core/entities/provider_configuration.py
agent_manager_sdk/core/entities/provider_entities.py
agent_manager_sdk/core/errors/__init__.py
agent_manager_sdk/core/errors/error.py
agent_manager_sdk/core/file/__init__.py
agent_manager_sdk/core/file/file_obj.py
agent_manager_sdk-0.1.2.dist-info/METADATA
agent_manager_sdk-0.1.2.dist-info/WHEEL
agent_manager_sdk-0.1.2.dist-info/entry_points.txt
agent_manager_sdk-0.1.2.dist-info/top_level.txt
agent_manager_sdk-0.1.2.dist-info/RECORD
