Metadata-Version: 2.4
Name: agent-manager-sdk
Version: 0.1.2
Summary: SDK for building and executing agent workflows
Author-email: Aum Javalgikar <aumjavalgikar@gmail.com>
License: MIT
Classifier: Development Status :: 3 - Alpha
Classifier: Intended Audience :: Developers
Classifier: Programming Language :: Python :: 3
Classifier: Programming Language :: Python :: 3.8
Classifier: Programming Language :: Python :: 3.9
Classifier: Programming Language :: Python :: 3.10
Requires-Python: >=3.10
Requires-Dist: flask==2.0.1
Requires-Dist: werkzeug==2.0.1
Requires-Dist: flask-restful==0.3.10
Requires-Dist: flask-cors==4.0.1
Requires-Dist: flask-login==0.6.3
Requires-Dist: flask-sqlalchemy==2.5.1
Requires-Dist: sqlalchemy==1.4.27
Requires-Dist: flask-migrate==3.1.0
Requires-Dist: celery==5.3.6
Requires-Dist: uvicorn==0.24.0.post1
Requires-Dist: nest-asyncio==1.6.0
Requires-Dist: python-dotenv==1.0.1
Requires-Dist: pyyaml==6.0.1
Requires-Dist: requests==2.32.3
Requires-Dist: yarl==1.9.4
Requires-Dist: redis==4.6.0
Requires-Dist: openai==1.35.10
Requires-Dist: tabulate==0.9.0
Requires-Dist: httpx==0.27.2
Provides-Extra: dev
Requires-Dist: pytest>=6.0.0; extra == "dev"
Requires-Dist: black>=21.0; extra == "dev"
Requires-Dist: flake8>=3.9.0; extra == "dev"
